vit_image_retrieval/__init__.py
vit_image_retrieval/cli.py
vit_image_retrieval/main.py
vit_image_retrieval/core/__init__.py
vit_image_retrieval/core/feature_extractor.py
vit_image_retrieval/core/image_display.py
vit_image_retrieval/core/retrieval_system.py
vit_image_retrieval/gui/__init__.py
vit_image_retrieval/gui/main_app.py
vit_image_retrieval-1.2.0.dist-info/LICENSE
vit_image_retrieval-1.2.0.dist-info/METADATA
vit_image_retrieval-1.2.0.dist-info/WHEEL
vit_image_retrieval-1.2.0.dist-info/entry_points.txt
vit_image_retrieval-1.2.0.dist-info/top_level.txt
vit_image_retrieval-1.2.0.dist-info/RECORD
