Metadata-Version: 2.1
Name: vit-image-retrieval
Version: 1.2.0
Summary: A Vision Transformer based image retrieval system
Home-page: https://github.com/bnsreenu/vit-image-retrieval
Author: Dr. Sreenivas Bhattiprolu
Author-email: pythonformicroscopists@google.com
Project-URL: Bug Tracker, https://github.com/bnsreenu/vit-image-retrieval/issues
Requires-Python: >=3.8
License-File: LICENSE
Requires-Dist: torch>=2.0.0
Requires-Dist: torchvision>=0.15.0
Requires-Dist: faiss-cpu>=1.7.4
Requires-Dist: Pillow>=9.0.0
Requires-Dist: numpy>=1.20.0
Requires-Dist: PyQt5>=5.15.0
